{"nodes": [{"id": "c_business_pult_gstack_test_skill_e2e_learnings_test_ts", "label": "skill-e2e-learnings.test.ts", "file_type": "code", "source_file": "C:\\business-pult\\gstack\\test\\skill-e2e-learnings.test.ts", "source_location": "L1"}, {"id": "test_skill_e2e_learnings_test_run", "label": "run()", "file_type": "code", "source_file": "C:\\business-pult\\gstack\\test\\skill-e2e-learnings.test.ts", "source_location": "L27"}], "edges": [{"source": "c_business_pult_gstack_test_skill_e2e_learnings_test_ts", "target": "bun_test", "relation": "imports_from", "context": "import", "confidence": "EXTRACTED", "source_file": "C:\\business-pult\\gstack\\test\\skill-e2e-learnings.test.ts", "source_location": "L1", "weight": 1.0}, {"source": "c_business_pult_gstack_test_skill_e2e_learnings_test_ts", "target": "c_business_pult_gstack_test_helpers_session_runner", "relation": "imports_from", "context": "import", "confidence": "EXTRACTED", "source_file": "C:\\business-pult\\gstack\\test\\skill-e2e-learnings.test.ts", "source_location": "L2", "weight": 1.0}, {"source": "c_business_pult_gstack_test_skill_e2e_learnings_test_ts", "target": "helpers_session_runner_runskilltest", "relation": "imports", "context": "import", "confidence": "EXTRACTED", "source_file": "C:\\business-pult\\gstack\\test\\skill-e2e-learnings.test.ts", "source_location": "L2", "weight": 1.0}, {"source": "c_business_pult_gstack_test_skill_e2e_learnings_test_ts", "target": "c_business_pult_gstack_test_helpers_e2e_helpers", "relation": "imports_from", "context": "import", "confidence": "EXTRACTED", "source_file": "C:\\business-pult\\gstack\\test\\skill-e2e-learnings.test.ts", "source_location": "L3", "weight": 1.0}, {"source": "c_business_pult_gstack_test_skill_e2e_learnings_test_ts", "target": "helpers_e2e_helpers_root", "relation": "imports", "context": "import", "confidence": "EXTRACTED", "source_file": "C:\\business-pult\\gstack\\test\\skill-e2e-learnings.test.ts", "source_location": "L3", "weight": 1.0}, {"source": "c_business_pult_gstack_test_skill_e2e_learnings_test_ts", "target": "helpers_e2e_helpers_runid", "relation": "imports", "context": "import", "confidence": "EXTRACTED", "source_file": "C:\\business-pult\\gstack\\test\\skill-e2e-learnings.test.ts", "source_location": "L3", "weight": 1.0}, {"source": "c_business_pult_gstack_test_skill_e2e_learnings_test_ts", "target": "helpers_e2e_helpers_evalsenabled", "relation": "imports", "context": "import", "confidence": "EXTRACTED", "source_file": "C:\\business-pult\\gstack\\test\\skill-e2e-learnings.test.ts", "source_location": "L3", "weight": 1.0}, {"source": "c_business_pult_gstack_test_skill_e2e_learnings_test_ts", "target": "helpers_e2e_helpers_describeifselected", "relation": "imports", "context": "import", "confidence": "EXTRACTED", "source_file": "C:\\business-pult\\gstack\\test\\skill-e2e-learnings.test.ts", "source_location": "L3", "weight": 1.0}, {"source": "c_business_pult_gstack_test_skill_e2e_learnings_test_ts", "target": "helpers_e2e_helpers_testconcurrentifselected", "relation": "imports", "context": "import", "confidence": "EXTRACTED", "source_file": "C:\\business-pult\\gstack\\test\\skill-e2e-learnings.test.ts", "source_location": "L3", "weight": 1.0}, {"source": "c_business_pult_gstack_test_skill_e2e_learnings_test_ts", "target": "helpers_e2e_helpers_copydirsync", "relation": "imports", "context": "import", "confidence": "EXTRACTED", "source_file": "C:\\business-pult\\gstack\\test\\skill-e2e-learnings.test.ts", "source_location": "L3", "weight": 1.0}, {"source": "c_business_pult_gstack_test_skill_e2e_learnings_test_ts", "target": "helpers_e2e_helpers_logcost", "relation": "imports", "context": "import", "confidence": "EXTRACTED", "source_file": "C:\\business-pult\\gstack\\test\\skill-e2e-learnings.test.ts", "source_location": "L3", "weight": 1.0}, {"source": "c_business_pult_gstack_test_skill_e2e_learnings_test_ts", "target": "helpers_e2e_helpers_recorde2e", "relation": "imports", "context": "import", "confidence": "EXTRACTED", "source_file": "C:\\business-pult\\gstack\\test\\skill-e2e-learnings.test.ts", "source_location": "L3", "weight": 1.0}, {"source": "c_business_pult_gstack_test_skill_e2e_learnings_test_ts", "target": "helpers_e2e_helpers_createevalcollector", "relation": "imports", "context": "import", "confidence": "EXTRACTED", "source_file": "C:\\business-pult\\gstack\\test\\skill-e2e-learnings.test.ts", "source_location": "L3", "weight": 1.0}, {"source": "c_business_pult_gstack_test_skill_e2e_learnings_test_ts", "target": "helpers_e2e_helpers_finalizeevalcollector", "relation": "imports", "context": "import", "confidence": "EXTRACTED", "source_file": "C:\\business-pult\\gstack\\test\\skill-e2e-learnings.test.ts", "source_location": "L3", "weight": 1.0}, {"source": "c_business_pult_gstack_test_skill_e2e_learnings_test_ts", "target": "child_process", "relation": "imports_from", "context": "import", "confidence": "EXTRACTED", "source_file": "C:\\business-pult\\gstack\\test\\skill-e2e-learnings.test.ts", "source_location": "L9", "weight": 1.0}, {"source": "c_business_pult_gstack_test_skill_e2e_learnings_test_ts", "target": "fs", "relation": "imports_from", "context": "import", "confidence": "EXTRACTED", "source_file": "C:\\business-pult\\gstack\\test\\skill-e2e-learnings.test.ts", "source_location": "L10", "weight": 1.0}, {"source": "c_business_pult_gstack_test_skill_e2e_learnings_test_ts", "target": "path", "relation": "imports_from", "context": "import", "confidence": "EXTRACTED", "source_file": "C:\\business-pult\\gstack\\test\\skill-e2e-learnings.test.ts", "source_location": "L11", "weight": 1.0}, {"source": "c_business_pult_gstack_test_skill_e2e_learnings_test_ts", "target": "os", "relation": "imports_from", "context": "import", "confidence": "EXTRACTED", "source_file": "C:\\business-pult\\gstack\\test\\skill-e2e-learnings.test.ts", "source_location": "L12", "weight": 1.0}, {"source": "c_business_pult_gstack_test_skill_e2e_learnings_test_ts", "target": "test_skill_e2e_learnings_test_run", "relation": "contains", "confidence": "EXTRACTED", "source_file": "C:\\business-pult\\gstack\\test\\skill-e2e-learnings.test.ts", "source_location": "L27", "weight": 1.0}], "raw_calls": [{"caller_nid": "test_skill_e2e_learnings_test_run", "callee": "spawnSync", "is_member_call": false, "source_file": "C:\\business-pult\\gstack\\test\\skill-e2e-learnings.test.ts", "source_location": "L28"}]}